steamstore/__init__.py
steamstore/app.py
steamstore/client.py
steamstore/defaults.py
steamstore/featured.py
steamstore-0.0.6.dist-info/LICENSE
steamstore-0.0.6.dist-info/WHEEL
steamstore-0.0.6.dist-info/METADATA
steamstore-0.0.6.dist-info/RECORD
