Metadata-Version: 2.1
Name: steamstore
Version: 0.0.6
Summary: steamstore.py - A Python wrapper for the Public Steam StoreFront API
Home-page: https://github.com/saucesteals/steamstore
License: UNKNOWN
Author: Sauce
Author-email: saucesteals@gmail.com
Requires-Python: >=3.6
Classifier: Programming Language :: Python :: 3
Classifier: License :: OSI Approved :: MIT License
Classifier: Operating System :: OS Independent
